README.md
setup.py
amlfbp/__init__.py
amlfbp/__main__.py
amlfbp/code_process.py
amlfbp/config.py
amlfbp/helpers.py
amlfbp/pipeline.py
amlfbp/testing.py
amlfbp.egg-info/PKG-INFO
amlfbp.egg-info/SOURCES.txt
amlfbp.egg-info/dependency_links.txt
amlfbp.egg-info/entry_points.txt
amlfbp.egg-info/requires.txt
amlfbp.egg-info/top_level.txt