Metadata-Version: 1.0
Name: amlfbp
Version: 0.43
Summary: Azure Machine Learning service compute for Busy People. See more in the Github
Home-page: https://github.com/alekscallebat/amlfbp
Author: Aleksander Callebat
Author-email: aleks_callebat@hotmail.fr
License: UNKNOWN
Platform: UNKNOWN
